{
  "fisherman": {"ar": "صياد سمك", "arPhonetic": "say-YAAD SA-mak"},
  "hunter": {"ar": "صياد", "arPhonetic": "say-YAAD"},
  "gardener": {"ar": "بستاني", "arPhonetic": "bus-TAA-nee"},
  "designer": {"ar": "مصمم", "arPhonetic": "mu-SAM-mim"},
  "photographer": {"ar": "مصوّر", "arPhonetic": "mu-SAW-wir"},
  "operator": {"ar": "مشغّل", "arPhonetic": "mu-SHAGH-ghil"},
  "dispatcher": {"ar": "مُرسِل", "arPhonetic": "MUR-sil"},
  "cashier": {"ar": "أمين صندوق", "arPhonetic": "a-MEEN sun-DOOQ"},
  "stream/brook": {"ar": "جدول صغير", "arPhonetic": "JAD-wal sa-GHEER"},
  "hill": {"ar": "تل", "arPhonetic": "TALL"},
  "cliff": {"ar": "جرف", "arPhonetic": "JURF"},
  "steppe": {"ar": "سهوب", "arPhonetic": "su-HOOB"},
  "taiga": {"ar": "تايغا", "arPhonetic": "TAA-ee-ghaa"},
  "tundra": {"ar": "تندرا", "arPhonetic": "TUN-draa"},
  "thunderstorm": {"ar": "عاصفة رعدية", "arPhonetic": "AA-si-fah RA-dee-yah"},
  "dawn/sunrise": {"ar": "فجر", "arPhonetic": "FAJR"},
  "mole": {"ar": "خلد", "arPhonetic": "KHULD"},
  "hawk": {"ar": "صقر", "arPhonetic": "SAQR"},
  "wild boar": {"ar": "خنزير بري", "arPhonetic": "khin-ZEER BAR-ree"},
  "beaver": {"ar": "قندس", "arPhonetic": "QUN-dus"},
  "badger": {"ar": "غرير", "arPhonetic": "ghu-REER"},
  "lynx": {"ar": "وشق", "arPhonetic": "WA-shaq"},
  "crane (bird)": {"ar": "كركي", "arPhonetic": "KUR-kee"},
  "rose": {"ar": "وردة", "arPhonetic": "WAR-dah"},
  "tulip": {"ar": "توليب", "arPhonetic": "too-LEEB"}
}
