{
  "psychology": {"ar": "علم النفس", "arPhonetic": "ILM an-NAFS"},
  "exam": {"ar": "امتحان", "arPhonetic": "im-ti-HAAN"},
  "test": {"ar": "اختبار", "arPhonetic": "ikh-ti-BAAR"},
  "grade/mark": {"ar": "درجة", "arPhonetic": "DA-ra-ja"},
  "homework": {"ar": "واجب منزلي", "arPhonetic": "WAA-jib man-ZI-lee"},
  "textbook": {"ar": "كتاب مدرسي", "arPhonetic": "ki-TAAB mad-RA-see"},
  "exercise book": {"ar": "دفتر", "arPhonetic": "DAF-tar"},
  "diary/daybook": {"ar": "مذكرة", "arPhonetic": "mu-DHAK-ki-ra"},
  "schedule/timetable": {"ar": "جدول", "arPhonetic": "JAD-wal"},
  "break/recess": {"ar": "استراحة", "arPhonetic": "is-ti-RAA-ha"},
  "class/classroom": {"ar": "فصل", "arPhonetic": "FASL"},
  "lecture hall": {"ar": "قاعة محاضرات", "arPhonetic": "QAA-at mu-haa-da-RAAT"},
  "lecture": {"ar": "محاضرة", "arPhonetic": "mu-HAA-da-ra"},
  "seminar": {"ar": "ندوة", "arPhonetic": "NAD-wa"},
  "dissertation/thesis": {"ar": "أطروحة", "arPhonetic": "ut-ROO-ha"},
  "diploma/degree": {"ar": "شهادة", "arPhonetic": "sha-HAA-da"},
  "scholarship/stipend": {"ar": "منحة دراسية", "arPhonetic": "MIN-ha di-raa-SEE-ya"},
  "student (university)": {"ar": "طالب جامعي", "arPhonetic": "TAA-lib jaa-mi-EE"},
  "pupil/student (school)": {"ar": "تلميذ", "arPhonetic": "til-MEEZ"},
  "lecturer/instructor": {"ar": "محاضر", "arPhonetic": "mu-HAA-dir"},
  "professor": {"ar": "أستاذ", "arPhonetic": "us-TAAZ"},
  "rector/chancellor": {"ar": "رئيس الجامعة", "arPhonetic": "ra-EES al-jaa-MI-a"},
  "principal/director": {"ar": "مدير", "arPhonetic": "mu-DEER"},
  "blackboard": {"ar": "سبورة", "arPhonetic": "sab-BOO-ra"},
  "chalk": {"ar": "طباشير", "arPhonetic": "ta-baa-SHEER"}
}
