[
  {
    "en": "cell (biology)",
    "uk": "клітина",
    "category": "science"
  },
  {
    "en": "gene",
    "uk": "ген",
    "category": "science"
  },
  {
    "en": "DNA",
    "uk": "ДНК",
    "category": "science"
  },
  {
    "en": "evolution",
    "uk": "еволюція",
    "category": "science"
  },
  {
    "en": "gravity",
    "uk": "гравітація",
    "category": "science"
  },
  {
    "en": "energy",
    "uk": "енергія",
    "category": "science"
  },
  {
    "en": "electricity",
    "uk": "електрика",
    "category": "science"
  },
  {
    "en": "magnet",
    "uk": "магніт",
    "category": "science"
  },
  {
    "en": "heat",
    "uk": "тепло",
    "category": "science"
  },
  {
    "en": "wave",
    "uk": "хвиля",
    "category": "science"
  },
  {
    "en": "particle",
    "uk": "частинка",
    "category": "science"
  },
  {
    "en": "universe",
    "uk": "всесвіт",
    "category": "science"
  },
  {
    "en": "galaxy",
    "uk": "галактика",
    "category": "science"
  },
  {
    "en": "planet",
    "uk": "планета",
    "category": "science"
  },
  {
    "en": "satellite",
    "uk": "супутник",
    "category": "science"
  },
  {
    "en": "space/cosmos",
    "uk": "космос",
    "category": "science"
  },
  {
    "en": "astronaut",
    "uk": "астронавт",
    "category": "science"
  },
  {
    "en": "telescope",
    "uk": "телескоп",
    "category": "science"
  },
  {
    "en": "laboratory",
    "uk": "лабораторія",
    "category": "science"
  },
  {
    "en": "discovery",
    "uk": "відкриття",
    "category": "science"
  },
  {
    "en": "invention",
    "uk": "винахід",
    "category": "science"
  },
  {
    "en": "robot",
    "uk": "робот",
    "category": "science"
  },
  {
    "en": "artificial intelligence",
    "uk": "штучний інтелект",
    "category": "science"
  },
  {
    "en": "melody",
    "uk": "мелодія",
    "category": "music-arts"
  },
  {
    "en": "rhythm",
    "uk": "ритм",
    "category": "music-arts"
  }
]