[
  {
    "en": "referee/judge",
    "uk": "суддя",
    "category": "sports"
  },
  {
    "en": "fan/supporter",
    "uk": "вболівальник",
    "category": "sports"
  },
  {
    "en": "athlete",
    "uk": "спортсмен",
    "category": "sports"
  },
  {
    "en": "goal (net)",
    "uk": "ворота",
    "category": "sports"
  },
  {
    "en": "court/playing field",
    "uk": "майданчик",
    "category": "sports"
  },
  {
    "en": "ice rink",
    "uk": "каток",
    "category": "sports"
  },
  {
    "en": "national team",
    "uk": "збірна",
    "category": "sports"
  },
  {
    "en": "final",
    "uk": "фінал",
    "category": "sports"
  },
  {
    "en": "semifinal",
    "uk": "півфінал",
    "category": "sports"
  },
  {
    "en": "trousers/pants",
    "uk": "штани",
    "category": "clothing"
  },
  {
    "en": "jacket",
    "uk": "куртка",
    "category": "clothing"
  },
  {
    "en": "hat/cap (winter)",
    "uk": "шапка",
    "category": "clothing"
  },
  {
    "en": "gloves",
    "uk": "рукавиці",
    "category": "clothing"
  },
  {
    "en": "boots/shoes",
    "uk": "черевики",
    "category": "clothing"
  },
  {
    "en": "boots (tall)",
    "uk": "чоботи",
    "category": "clothing"
  },
  {
    "en": "sneakers/trainers",
    "uk": "кросівки",
    "category": "clothing"
  },
  {
    "en": "tie/necktie",
    "uk": "краватка",
    "category": "clothing"
  },
  {
    "en": "jeans",
    "uk": "джинси",
    "category": "clothing"
  },
  {
    "en": "shorts",
    "uk": "шорти",
    "category": "clothing"
  },
  {
    "en": "tank top/undershirt",
    "uk": "майка",
    "category": "clothing"
  },
  {
    "en": "raincoat",
    "uk": "плащ",
    "category": "clothing"
  },
  {
    "en": "vest/waistcoat",
    "uk": "жилет",
    "category": "clothing"
  },
  {
    "en": "dress shoes",
    "uk": "туфлі",
    "category": "clothing"
  },
  {
    "en": "mittens",
    "uk": "рукавички",
    "category": "clothing"
  },
  {
    "en": "cinema/movies",
    "uk": "кіно",
    "category": "entertainment"
  }
]