[
  {
    "en": "tomorrow",
    "uk": "завтра",
    "category": "time"
  },
  {
    "en": "now",
    "uk": "зараз",
    "category": "time"
  },
  {
    "en": "then/later",
    "uk": "потім",
    "category": "time"
  },
  {
    "en": "earlier/before",
    "uk": "раніше",
    "category": "time"
  },
  {
    "en": "soon",
    "uk": "скоро",
    "category": "time"
  },
  {
    "en": "always",
    "uk": "завжди",
    "category": "time"
  },
  {
    "en": "never",
    "uk": "ніколи",
    "category": "time"
  },
  {
    "en": "sometimes",
    "uk": "іноді",
    "category": "time"
  },
  {
    "en": "often",
    "uk": "часто",
    "category": "time"
  },
  {
    "en": "rarely",
    "uk": "рідко",
    "category": "time"
  },
  {
    "en": "Monday",
    "uk": "понеділок",
    "category": "time"
  },
  {
    "en": "Tuesday",
    "uk": "вівторок",
    "category": "time"
  },
  {
    "en": "Wednesday",
    "uk": "середа",
    "category": "time"
  },
  {
    "en": "Thursday",
    "uk": "четвер",
    "category": "time"
  },
  {
    "en": "Friday",
    "uk": "п'ятниця",
    "category": "time"
  },
  {
    "en": "Saturday",
    "uk": "субота",
    "category": "time"
  },
  {
    "en": "Sunday",
    "uk": "неділя",
    "category": "time"
  },
  {
    "en": "January",
    "uk": "січень",
    "category": "time"
  },
  {
    "en": "February",
    "uk": "лютий",
    "category": "time"
  },
  {
    "en": "March",
    "uk": "березень",
    "category": "time"
  },
  {
    "en": "April",
    "uk": "квітень",
    "category": "time"
  },
  {
    "en": "May",
    "uk": "травень",
    "category": "time"
  },
  {
    "en": "June",
    "uk": "червень",
    "category": "time"
  },
  {
    "en": "July",
    "uk": "липень",
    "category": "time"
  },
  {
    "en": "August",
    "uk": "серпень",
    "category": "time"
  }
]