{
  "manicure": {"de": "Maniküre", "phoneticDe": "mah-nee-KOO-reh"},
  "pedicure": {"de": "Pediküre", "phoneticDe": "peh-dee-KOO-reh"},
  "hairstyle": {"de": "Frisur", "phoneticDe": "free-ZOOR"},
  "salon": {"de": "Salon/Friseursalon", "phoneticDe": "zah-LOHN/free-ZUR-zah-lohn"},
  "spa": {"de": "Spa/Wellnessbereich", "phoneticDe": "SPAH/VEL-nes-beh-rysh"},
  "massage": {"de": "Massage", "phoneticDe": "mah-SAH-zheh"},
  "aromatherapy": {"de": "Aromatherapie", "phoneticDe": "ah-roh-mah-teh-rah-PEE"},
  "disaster": {"de": "Katastrophe/Desaster", "phoneticDe": "kah-tah-STRO-feh/deh-ZAHS-ter"},
  "emergency": {"de": "Notfall", "phoneticDe": "NOHT-fahl"},
  "rescue": {"de": "Rettung", "phoneticDe": "RET-toong"},
  "evacuation": {"de": "Evakuierung", "phoneticDe": "eh-vah-koo-EER-oong"},
  "shelter": {"de": "Schutzraum/Unterkunft", "phoneticDe": "SHOOTS-raum/OON-ter-koonft"},
  "siren": {"de": "Sirene", "phoneticDe": "zee-RAY-neh"},
  "alarm": {"de": "Alarm", "phoneticDe": "ah-LARM"},
  "fire truck": {"de": "Feuerwehrauto", "phoneticDe": "FOY-er-vair-au-to"},
  "paramedic": {"de": "Sanitäter/Rettungssanitäter", "phoneticDe": "zah-nee-TAY-ter/RET-toongs-zah-nee-tay-ter"},
  "first aid": {"de": "Erste Hilfe", "phoneticDe": "AIR-steh HIL-feh"},
  "stretcher": {"de": "Trage/Bahre", "phoneticDe": "TRAH-geh/BAH-reh"},
  "oxygen": {"de": "Sauerstoff", "phoneticDe": "ZAU-er-shtof"},
  "fire extinguisher": {"de": "Feuerlöscher", "phoneticDe": "FOY-er-lur-sher"},
  "hydrant": {"de": "Hydrant", "phoneticDe": "hoo-DRAHNT"},
  "explosion": {"de": "Explosion", "phoneticDe": "eks-plo-TSEE-ohn"},
  "collapse": {"de": "Einsturz/Zusammenbruch", "phoneticDe": "EYEN-shtorts/tsoo-ZAH-men-brookh"},
  "wreckage/debris": {"de": "Trümmer/Wrack", "phoneticDe": "TROOM-mer/VRAHK"},
  "survivor": {"de": "Überlebender", "phoneticDe": "OO-ber-lay-ben-der"}
}
