{
  "bowling": {"es": "bolos", "phoneticEs": "BO-los"},
  "accelerator": {"es": "acelerador", "phoneticEs": "a-se-le-ra-DOR"},
  "bumper": {"es": "parachoques", "phoneticEs": "pa-ra-CHO-kes"},
  "hood (car)": {"es": "capó", "phoneticEs": "ka-PO"},
  "trunk (car)": {"es": "maletero", "phoneticEs": "ma-le-TE-ro"},
  "headlight": {"es": "faro", "phoneticEs": "FA-ro"},
  "taillight": {"es": "luz trasera", "phoneticEs": "LUS tra-SE-ra"},
  "windshield": {"es": "parabrisas", "phoneticEs": "pa-ra-BRI-sas"},
  "wiper": {"es": "limpiaparabrisas", "phoneticEs": "lim-pya-pa-ra-BRI-sas"},
  "seatbelt": {"es": "cinturón de seguridad", "phoneticEs": "sin-tu-RON de se-gu-ri-DAD"},
  "airbag": {"es": "airbag", "phoneticEs": "AIR-bag"},
  "dashboard": {"es": "tablero", "phoneticEs": "ta-BLE-ro"},
  "speedometer": {"es": "velocímetro", "phoneticEs": "be-lo-SI-me-tro"},
  "fuel": {"es": "combustible", "phoneticEs": "kom-bus-TI-ble"},
  "gasoline": {"es": "gasolina", "phoneticEs": "ga-so-LI-na"},
  "exhaust pipe": {"es": "tubo de escape", "phoneticEs": "TU-bo de es-KA-pe"},
  "muffler": {"es": "silenciador", "phoneticEs": "si-len-sya-DOR"},
  "transmission": {"es": "transmisión", "phoneticEs": "trans-mi-SYON"},
  "clutch": {"es": "embrague", "phoneticEs": "em-BRA-ge"},
  "gear": {"es": "marcha", "phoneticEs": "MAR-cha"},
  "highway": {"es": "autopista", "phoneticEs": "au-to-PIS-ta"},
  "intersection": {"es": "intersección", "phoneticEs": "in-ter-sek-SYON"},
  "lens": {"es": "lente", "phoneticEs": "LEN-te"},
  "focus": {"es": "enfoque", "phoneticEs": "en-FO-ke"},
  "exposure": {"es": "exposición", "phoneticEs": "eks-po-si-SYON"}
}
