{
  "external/outer": { "zh": "外部的", "zhPhonetic": "wàibù de" },
  "internal/inner": { "zh": "内部的", "zhPhonetic": "nèibù de" },
  "front": { "zh": "前面的", "zhPhonetic": "qiánmiàn de" },
  "rear/back": { "zh": "后面的", "zhPhonetic": "hòumiàn de" },
  "right (side)": { "zh": "右边的", "zhPhonetic": "yòubiān de" },
  "left (side)": { "zh": "左边的", "zhPhonetic": "zuǒbiān de" },
  "central": { "zh": "中央的", "zhPhonetic": "zhōngyāng de" },
  "main/chief": { "zh": "主要的", "zhPhonetic": "zhǔyào de" },
  "secondary/minor": { "zh": "次要的", "zhPhonetic": "cìyào de" },
  "additional/extra": { "zh": "额外的", "zhPhonetic": "éwài de" },
  "basic/fundamental": { "zh": "基本的", "zhPhonetic": "jīběn de" },
  "initial/beginning": { "zh": "最初的", "zhPhonetic": "zuìchū de" },
  "final/end": { "zh": "最终的", "zhPhonetic": "zuìzhōng de" },
  "temporary": { "zh": "临时的", "zhPhonetic": "línshí de" },
  "permanent/constant": { "zh": "永久的", "zhPhonetic": "yǒngjiǔ de" },
  "daily": { "zh": "每日的", "zhPhonetic": "měirì de" },
  "weekly": { "zh": "每周的", "zhPhonetic": "měizhōu de" },
  "monthly": { "zh": "每月的", "zhPhonetic": "měiyuè de" },
  "annual/yearly": { "zh": "每年的", "zhPhonetic": "měinián de" },
  "common/shared": { "zh": "共同的", "zhPhonetic": "gòngtóng de" },
  "own/personal": { "zh": "自己的", "zhPhonetic": "zìjǐ de" },
  "separate/individual": { "zh": "单独的", "zhPhonetic": "dāndú de" },
  "general/overall": { "zh": "总体的", "zhPhonetic": "zǒngtǐ de" },
  "specific/concrete": { "zh": "具体的", "zhPhonetic": "jùtǐ de" },
  "abstract": { "zh": "抽象的", "zhPhonetic": "chōuxiàng de" }
}
