{
  "elections": { "zh": "选举", "zhPhonetic": "xuǎnjǔ" },
  "party (political)": { "zh": "政党", "zhPhonetic": "zhèngdǎng" },
  "democracy": { "zh": "民主", "zhPhonetic": "mínzhǔ" },
  "court": { "zh": "法院", "zhPhonetic": "fǎyuàn" },
  "crime": { "zh": "犯罪", "zhPhonetic": "fànzuì" },
  "punishment": { "zh": "惩罚", "zhPhonetic": "chéngfá" },
  "prison": { "zh": "监狱", "zhPhonetic": "jiānyù" },
  "police": { "zh": "警察", "zhPhonetic": "jǐngchá" },
  "witness": { "zh": "证人", "zhPhonetic": "zhèngrén" },
  "evidence/proof": { "zh": "证据", "zhPhonetic": "zhèngjù" },
  "fine/penalty": { "zh": "罚款", "zhPhonetic": "fákuǎn" },
  "document": { "zh": "文件", "zhPhonetic": "wénjiàn" },
  "ID/certificate": { "zh": "证件", "zhPhonetic": "zhèngjiàn" },
  "citizenship": { "zh": "公民身份", "zhPhonetic": "gōngmín shēnfèn" },
  "embassy": { "zh": "大使馆", "zhPhonetic": "dàshǐguǎn" },
  "consulate": { "zh": "领事馆", "zhPhonetic": "lǐngshìguǎn" },
  "diplomacy": { "zh": "外交", "zhPhonetic": "wàijiāo" },
  "treaty/agreement": { "zh": "条约", "zhPhonetic": "tiáoyuē" },
  "sanction": { "zh": "制裁", "zhPhonetic": "zhìcái" },
  "protest": { "zh": "抗议", "zhPhonetic": "kàngyì" },
  "rally/demonstration": { "zh": "示威", "zhPhonetic": "shìwēi" },
  "referendum": { "zh": "公投", "zhPhonetic": "gōngtóu" },
  "army": { "zh": "军队", "zhPhonetic": "jūnduì" },
  "military/troops": { "zh": "军事", "zhPhonetic": "jūnshì" },
  "navy/fleet": { "zh": "海军", "zhPhonetic": "hǎijūn" }
}
