{
  "census": { "zh": "人口普查", "zhPhonetic": "rénkǒu pǔchá" },
  "asylum/shelter": { "zh": "庇护所", "zhPhonetic": "bìhùsuǒ" },
  "ID card/identification": { "zh": "身份证", "zhPhonetic": "shēnfènzhèng" },
  "certificate": { "zh": "证书", "zhPhonetic": "zhèngshū" },
  "license": { "zh": "执照", "zhPhonetic": "zhízhào" },
  "permit/permission": { "zh": "许可", "zhPhonetic": "xǔkě" },
  "petition": { "zh": "请愿书", "zhPhonetic": "qǐngyuànshū" },
  "rally/protest": { "zh": "集会", "zhPhonetic": "jíhuì" },
  "demonstration/march": { "zh": "游行", "zhPhonetic": "yóuxíng" },
  "strike": { "zh": "罢工", "zhPhonetic": "bàgōng" },
  "trade union": { "zh": "工会", "zhPhonetic": "gōnghuì" },
  "right (legal)": { "zh": "权利", "zhPhonetic": "quánlì" },
  "dishonest/lying": { "zh": "不诚实的", "zhPhonetic": "bù chéngshí de" },
  "rude/rough": { "zh": "粗鲁的", "zhPhonetic": "cūlǔ de" },
  "persistent/determined": { "zh": "坚持不懈的", "zhPhonetic": "jiānchí bùxiè de" },
  "devoted/loyal": { "zh": "忠诚的", "zhPhonetic": "zhōngchéng de" },
  "treacherous/cunning": { "zh": "阴险的", "zhPhonetic": "yīnxiǎn de" },
  "foolish/silly": { "zh": "愚蠢的", "zhPhonetic": "yúchǔn de" },
  "curious/inquisitive": { "zh": "好奇的", "zhPhonetic": "hàoqí de" },
  "indifferent/apathetic": { "zh": "冷漠的", "zhPhonetic": "lěngmò de" },
  "vulnerable/sensitive": { "zh": "脆弱的", "zhPhonetic": "cuìruò de" },
  "resilient/stable": { "zh": "坚韧的", "zhPhonetic": "jiānrèn de" },
  "flexible": { "zh": "灵活的", "zhPhonetic": "línghuó de" },
  "rigid/stiff": { "zh": "僵硬的", "zhPhonetic": "jiāngyìng de" },
  "rough/coarse": { "zh": "粗糙的", "zhPhonetic": "cūcāo de" }
}
