{
  "something": { "zh": "某事", "zhPhonetic": "mǒu shì" },
  "someone": { "zh": "某人", "zhPhonetic": "mǒu rén" },
  "each/every": { "zh": "每个", "zhPhonetic": "měi gè" },
  "other/another": { "zh": "其他", "zhPhonetic": "qítā" },
  "self/oneself": { "zh": "自己", "zhPhonetic": "zìjǐ" },
  "in/into": { "zh": "在...里", "zhPhonetic": "zài...lǐ" },
  "in/at": { "zh": "在", "zhPhonetic": "zài" },
  "on/onto/at": { "zh": "在...上", "zhPhonetic": "zài...shàng" },
  "with/from": { "zh": "和", "zhPhonetic": "hé" },
  "to/until/before": { "zh": "到", "zhPhonetic": "dào" },
  "from": { "zh": "从", "zhPhonetic": "cóng" },
  "behind/for/beyond": { "zh": "在...后面", "zhPhonetic": "zài...hòumiàn" },
  "under": { "zh": "在...下面", "zhPhonetic": "zài...xiàmiàn" },
  "above/over": { "zh": "在...上面", "zhPhonetic": "zài...shàngmiàn" },
  "between": { "zh": "在...之间", "zhPhonetic": "zài...zhījiān" },
  "in front of/before": { "zh": "在...前面", "zhPhonetic": "zài...qiánmiàn" },
  "after": { "zh": "以后", "zhPhonetic": "yǐhòu" },
  "through/across/because of": { "zh": "通过", "zhPhonetic": "tōngguò" },
  "near/beside": { "zh": "旁边", "zhPhonetic": "pángbiān" },
  "around": { "zh": "周围", "zhPhonetic": "zhōuwéi" },
  "without": { "zh": "没有", "zhPhonetic": "méiyǒu" },
  "for": { "zh": "为了", "zhPhonetic": "wèile" },
  "about/concerning": { "zh": "关于", "zhPhonetic": "guānyú" },
  "and": { "zh": "和", "zhPhonetic": "hé" },
  "or": { "zh": "或者", "zhPhonetic": "huòzhě" }
}
