{
  "train car/carriage": { "zh": "车厢", "zhPhonetic": "chēxiāng" },
  "port/harbor": { "zh": "港口", "zhPhonetic": "gǎngkǒu" },
  "headquarters/staff": { "zh": "司令部", "zhPhonetic": "sīlìngbù" },
  "colonel": { "zh": "上校", "zhPhonetic": "shàngxiào" },
  "attack": { "zh": "攻击", "zhPhonetic": "gōngjī" },
  "peace/world": { "zh": "和平", "zhPhonetic": "hépíng" },
  "defeat": { "zh": "失败", "zhPhonetic": "shībài" },
  "fleet/navy": { "zh": "舰队", "zhPhonetic": "jiànduì" },
  "infantry": { "zh": "步兵", "zhPhonetic": "bùbīng" },
  "artillery": { "zh": "炮兵", "zhPhonetic": "pàobīng" },
  "aviation/air force": { "zh": "空军", "zhPhonetic": "kōngjūn" },
  "barracks": { "zh": "军营", "zhPhonetic": "jūnyíng" },
  "border": { "zh": "边境", "zhPhonetic": "biānjìng" },
  "cartridge/bullet": { "zh": "子弹", "zhPhonetic": "zǐdàn" },
  "assault rifle/automatic weapon": { "zh": "步枪", "zhPhonetic": "bùqiāng" },
  "pistol": { "zh": "手枪", "zhPhonetic": "shǒuqiāng" },
  "sniper": { "zh": "狙击手", "zhPhonetic": "jūjīshǒu" },
  "airborne troops/landing": { "zh": "空降兵", "zhPhonetic": "kōngjiàngbīng" },
  "guard/sentry": { "zh": "哨兵", "zhPhonetic": "shàobīng" },
  "military exercises": { "zh": "军事演习", "zhPhonetic": "jūnshì yǎnxí" },
  "military oath": { "zh": "军事誓言", "zhPhonetic": "jūnshì shìyán" },
  "lieutenant": { "zh": "中尉", "zhPhonetic": "zhōngwèi" },
  "captain": { "zh": "上尉", "zhPhonetic": "shàngwèi" },
  "major": { "zh": "少校", "zhPhonetic": "shàoxiào" },
  "marshal": { "zh": "元帅", "zhPhonetic": "yuánshuài" }
}
