{
  "passenger": { "ja": "乗客", "jaPhonetic": "JOU-kya-ku" },
  "pedestrian": { "ja": "歩行者", "jaPhonetic": "HO-kou-sha" },
  "tourist": { "ja": "観光客", "jaPhonetic": "KAN-kou-kya-ku" },
  "buyer": { "ja": "買い手", "jaPhonetic": "KA-i-te" },
  "victim": { "ja": "被害者", "jaPhonetic": "HI-gai-sha" },
  "criminal": { "ja": "犯罪者", "jaPhonetic": "HAN-zai-sha" },
  "refugee": { "ja": "難民", "jaPhonetic": "NAN-min" },
  "immigrant": { "ja": "移民", "jaPhonetic": "I-min" },
  "volunteer": { "ja": "ボランティア", "jaPhonetic": "BO-ran-ti-a" },
  "engine": { "ja": "エンジン", "jaPhonetic": "EN-jin" },
  "wheel": { "ja": "車輪", "jaPhonetic": "SHA-rin" },
  "tire": { "ja": "タイヤ", "jaPhonetic": "TAI-ya" },
  "steering wheel": { "ja": "ハンドル", "jaPhonetic": "HAN-do-ru" },
  "brake": { "ja": "ブレーキ", "jaPhonetic": "BU-REE-ki" },
  "gasoline/petrol": { "ja": "ガソリン", "jaPhonetic": "GA-so-rin" },
  "diesel": { "ja": "ディーゼル", "jaPhonetic": "DII-ze-ru" },
  "gas station": { "ja": "ガソリンスタンド", "jaPhonetic": "GA-so-rin-su-tan-do" },
  "parking": { "ja": "駐車場", "jaPhonetic": "CHUU-sha-jou" },
  "traffic light": { "ja": "信号", "jaPhonetic": "SHIN-gou" },
  "crosswalk": { "ja": "横断歩道", "jaPhonetic": "OU-dan-ho-dou" },
  "road sign": { "ja": "道路標識", "jaPhonetic": "DOU-ro-hyou-shi-ki" },
  "speed limit": { "ja": "速度制限", "jaPhonetic": "SO-ku-do-SEI-gen" },
  "accident/crash": { "ja": "事故", "jaPhonetic": "JI-ko" },
  "tow truck": { "ja": "レッカー車", "jaPhonetic": "REK-kaa-sha" },
  "driver's license": { "ja": "運転免許証", "jaPhonetic": "UN-ten-MEN-kyo-shou" }
}
