{
  "to dig": { "ja": "掘る", "jaPhonetic": "ho-RU" },
  "to cut (hair)/to mow": { "ja": "刈る", "jaPhonetic": "ka-RU" },
  "to stroll/to hang out": { "ja": "散歩する", "jaPhonetic": "SAN-po su-ru" },
  "to rest/to relax": { "ja": "休む", "jaPhonetic": "yasu-MU" },
  "to celebrate": { "ja": "祝う", "jaPhonetic": "iwa-U" },
  "to photograph": { "ja": "写真を撮る", "jaPhonetic": "SHA-shin o to-RU" },
  "to type": { "ja": "タイピングする", "jaPhonetic": "TAI-pin-gu su-ru" },
  "to vote": { "ja": "投票する", "jaPhonetic": "TOO-hyoo su-ru" },
  "to manage/to drive": { "ja": "管理する", "jaPhonetic": "KAN-ri su-ru" },
  "to organize": { "ja": "整理する", "jaPhonetic": "SEE-ri su-ru" },
  "to plan": { "ja": "計画する", "jaPhonetic": "KEE-kaku su-ru" },
  "to control": { "ja": "制御する", "jaPhonetic": "SEE-gyo su-ru" },
  "to defend/to protect": { "ja": "守る", "jaPhonetic": "mamo-RU" },
  "to attack": { "ja": "攻撃する", "jaPhonetic": "KOO-geki su-ru" },
  "to win/to defeat": { "ja": "勝つ", "jaPhonetic": "ka-TSU" },
  "to lose (a game)": { "ja": "負ける", "jaPhonetic": "ma-KE-ru" },
  "to train/to practice": { "ja": "練習する", "jaPhonetic": "REN-shuu su-ru" },
  "to compete": { "ja": "競争する", "jaPhonetic": "KYOO-soo su-ru" },
  "to worry": { "ja": "心配する", "jaPhonetic": "SHIN-pai su-ru" },
  "to envy": { "ja": "羨む", "jaPhonetic": "uray-MA-su" },
  "to hate": { "ja": "憎む", "jaPhonetic": "niku-MU" },
  "to trust": { "ja": "信じる", "jaPhonetic": "shin-JI-ru" },
  "to suspect": { "ja": "疑う", "jaPhonetic": "utaga-U" },
  "to be surprised": { "ja": "驚く", "jaPhonetic": "odoro-KU" },
  "to regret": { "ja": "後悔する", "jaPhonetic": "KOO-kai su-ru" }
}
