{
  "elections": { "ja": "選挙", "jaPhonetic": "senkyo" },
  "party (political)": { "ja": "政党", "jaPhonetic": "seitou" },
  "democracy": { "ja": "民主主義", "jaPhonetic": "minshu shugi" },
  "court": { "ja": "裁判所", "jaPhonetic": "saibansho" },
  "crime": { "ja": "犯罪", "jaPhonetic": "hanzai" },
  "punishment": { "ja": "罰", "jaPhonetic": "batsu" },
  "prison": { "ja": "刑務所", "jaPhonetic": "keimusho" },
  "police": { "ja": "警察", "jaPhonetic": "keisatsu" },
  "witness": { "ja": "証人", "jaPhonetic": "shounin" },
  "evidence/proof": { "ja": "証拠", "jaPhonetic": "shouko" },
  "fine/penalty": { "ja": "罰金", "jaPhonetic": "bakkin" },
  "document": { "ja": "書類", "jaPhonetic": "shorui" },
  "ID/certificate": { "ja": "身分証明書", "jaPhonetic": "mibun shoumeisho" },
  "citizenship": { "ja": "市民権", "jaPhonetic": "shiminken" },
  "embassy": { "ja": "大使館", "jaPhonetic": "taishikan" },
  "consulate": { "ja": "領事館", "jaPhonetic": "ryoujikan" },
  "diplomacy": { "ja": "外交", "jaPhonetic": "gaikou" },
  "treaty/agreement": { "ja": "条約", "jaPhonetic": "jouyaku" },
  "sanction": { "ja": "制裁", "jaPhonetic": "seisai" },
  "protest": { "ja": "抗議", "jaPhonetic": "kougi" },
  "rally/demonstration": { "ja": "デモ", "jaPhonetic": "demo" },
  "referendum": { "ja": "国民投票", "jaPhonetic": "kokumin touhyou" },
  "army": { "ja": "陸軍", "jaPhonetic": "rikugun" },
  "military/troops": { "ja": "軍隊", "jaPhonetic": "guntai" },
  "navy/fleet": { "ja": "海軍", "jaPhonetic": "kaigun" }
}
