{
  "hay": { "ja": "干し草", "jaPhonetic": "hoshikusa" },
  "plowed field/arable land": { "ja": "耕地", "jaPhonetic": "kouchi" },
  "sowing/seeding": { "ja": "種まき", "jaPhonetic": "tanemaki" },
  "rye": { "ja": "ライ麦", "jaPhonetic": "raimugi" },
  "oats": { "ja": "オート麦", "jaPhonetic": "ootomugi" },
  "barley": { "ja": "大麦", "jaPhonetic": "oomugi" },
  "plow": { "ja": "鋤", "jaPhonetic": "suki" },
  "combine harvester": { "ja": "コンバイン", "jaPhonetic": "konbain" },
  "greenhouse": { "ja": "温室", "jaPhonetic": "onshitsu" },
  "vegetable garden": { "ja": "菜園", "jaPhonetic": "saien" },
  "garden/orchard": { "ja": "果樹園", "jaPhonetic": "kajuen" },
  "vineyard": { "ja": "ブドウ園", "jaPhonetic": "budouen" },
  "pasture": { "ja": "牧草地", "jaPhonetic": "bokusōchi" },
  "cattle/livestock": { "ja": "家畜", "jaPhonetic": "kachiku" },
  "milkmaid": { "ja": "搾乳婦", "jaPhonetic": "sakunyūfu" },
  "beekeeper": { "ja": "養蜂家", "jaPhonetic": "yōhōka" },
  "irrigation/watering": { "ja": "灌漑", "jaPhonetic": "kangai" },
  "black soil/chernozem": { "ja": "黒土", "jaPhonetic": "kokudo" },
  "silage": { "ja": "サイレージ", "jaPhonetic": "sairēji" },
  "harvest/reaping": { "ja": "収穫", "jaPhonetic": "shūkaku" },
  "to sigh": { "ja": "ため息をつく", "jaPhonetic": "tameiki wo tsuku" },
  "to whistle": { "ja": "口笛を吹く", "jaPhonetic": "kuchibue wo fuku" },
  "to wheeze": { "ja": "ゼーゼーいう", "jaPhonetic": "zēzē iu" },
  "to groan/to moan": { "ja": "うめく", "jaPhonetic": "umeku" },
  "to snore": { "ja": "いびきをかく", "jaPhonetic": "ibiki wo kaku" }
}
