{
  "hay": {"ko": "건초", "koPhonetic": "GEON-cho"},
  "plowed field/arable land": {"ko": "경작지", "koPhonetic": "gyeong-JAK-ji"},
  "sowing/seeding": {"ko": "파종", "koPhonetic": "pa-JONG"},
  "rye": {"ko": "호밀", "koPhonetic": "HO-mil"},
  "oats": {"ko": "귀리", "koPhonetic": "GWI-ri"},
  "barley": {"ko": "보리", "koPhonetic": "BO-ri"},
  "plow": {"ko": "쟁기", "koPhonetic": "JAENG-gi"},
  "combine harvester": {"ko": "콤바인", "koPhonetic": "KOM-ba-in"},
  "greenhouse": {"ko": "온실", "koPhonetic": "ON-shil"},
  "vegetable garden": {"ko": "텃밭", "koPhonetic": "TEOT-bat"},
  "garden/orchard": {"ko": "정원", "koPhonetic": "JEONG-won"},
  "vineyard": {"ko": "포도원", "koPhonetic": "po-DO-won"},
  "pasture": {"ko": "목초지", "koPhonetic": "mok-CHO-ji"},
  "cattle/livestock": {"ko": "가축", "koPhonetic": "GA-chuk"},
  "milkmaid": {"ko": "착유부", "koPhonetic": "cha-GYU-bu"},
  "beekeeper": {"ko": "양봉가", "koPhonetic": "yang-BONG-ga"},
  "irrigation/watering": {"ko": "관개", "koPhonetic": "GWAN-geh"},
  "black soil/chernozem": {"ko": "흑토", "koPhonetic": "HEUK-to"},
  "silage": {"ko": "사일리지", "koPhonetic": "sa-IL-li-ji"},
  "harvest/reaping": {"ko": "수확", "koPhonetic": "SU-hwak"},
  "to sigh": {"ko": "한숨 쉬다", "koPhonetic": "han-sum SHI-da"},
  "to whistle": {"ko": "휘파람 불다", "koPhonetic": "hwi-pa-ram BUL-da"},
  "to wheeze": {"ko": "쌕쌕거리다", "koPhonetic": "ssek-ssek-GEO-ri-da"},
  "to groan/to moan": {"ko": "신음하다", "koPhonetic": "shin-EUM-ha-da"},
  "to snore": {"ko": "코골다", "koPhonetic": "ko-GOL-da"}
}
