{
  "evidence": {"ko": "증거", "koPhonetic": "JEUNG-geo"},
  "testimony": {"ko": "증언", "koPhonetic": "JEUNG-eon"},
  "defendant": {"ko": "피고인", "koPhonetic": "pi-GO-in"},
  "plaintiff": {"ko": "원고", "koPhonetic": "WON-go"},
  "prosecutor": {"ko": "검사", "koPhonetic": "GEOM-sa"},
  "appeal": {"ko": "항소", "koPhonetic": "HANG-so"},
  "bail": {"ko": "보석금", "koPhonetic": "bo-SEOK-geum"},
  "lawsuit": {"ko": "소송", "koPhonetic": "SO-song"},
  "clause": {"ko": "조항", "koPhonetic": "JO-hang"},
  "amendment": {"ko": "수정안", "koPhonetic": "su-JEONG-an"},
  "legislation": {"ko": "법률", "koPhonetic": "BEOM-nyul"},
  "surgery": {"ko": "수술", "koPhonetic": "SU-sul"},
  "operation (medical)": {"ko": "수술", "koPhonetic": "SU-sul"},
  "anesthesia": {"ko": "마취", "koPhonetic": "MA-chwi"},
  "prescription": {"ko": "처방전", "koPhonetic": "cheo-BANG-jeon"},
  "injection": {"ko": "주사", "koPhonetic": "JU-sa"},
  "ultrasound": {"ko": "초음파", "koPhonetic": "cho-EUM-pa"},
  "fever": {"ko": "열", "koPhonetic": "YEOL"},
  "sneeze": {"ko": "재채기", "koPhonetic": "jeh-CHEH-gi"},
  "dizziness": {"ko": "어지러움", "koPhonetic": "eo-ji-REO-um"},
  "nausea": {"ko": "메스꺼움", "koPhonetic": "me-seu-KKEO-um"},
  "rash": {"ko": "발진", "koPhonetic": "BAL-jin"},
  "scar": {"ko": "흉터", "koPhonetic": "HYUNG-teo"},
  "blister": {"ko": "물집", "koPhonetic": "MUL-jip"},
  "swelling": {"ko": "부기", "koPhonetic": "BU-gi"}
}
