{
  "comrade/companion": { "hi": "साथी", "hiPhonetic": "SAA-thee" },
  "plain": { "hi": "मैदान", "hiPhonetic": "MAI-daan" },
  "swamp": { "hi": "दलदल", "hiPhonetic": "DAL-dal" },
  "equator": { "hi": "भूमध्य रेखा", "hiPhonetic": "bhoo-MADH-ya RE-khaa" },
  "shore/coast": { "hi": "तट", "hiPhonetic": "TAT" },
  "mountain range": { "hi": "पर्वत श्रृंखला", "hiPhonetic": "PAR-vat SHRIN-kha-laa" },
  "nature reserve": { "hi": "अभयारण्य", "hiPhonetic": "ab-ha-YAA-ran-ya" },
  "polar circle": { "hi": "ध्रुवीय वृत्त", "hiPhonetic": "DHRU-vee-ya VRIT-ta" },
  "latitude": { "hi": "अक्षांश", "hiPhonetic": "AK-shaansh" },
  "longitude": { "hi": "देशांतर", "hiPhonetic": "de-SHAAN-tar" },
  "horizon": { "hi": "क्षितिज", "hiPhonetic": "KSHI-tij" },
  "franchise": { "hi": "फ़्रैंचाइज़ी", "hiPhonetic": "FRAIN-chai-zee" },
  "startup": { "hi": "स्टार्टअप", "hiPhonetic": "STAAR-tap" },
  "brand": { "hi": "ब्रांड", "hiPhonetic": "BRAAND" },
  "logo": { "hi": "लोगो", "hiPhonetic": "LO-go" },
  "consumer": { "hi": "उपभोक्ता", "hiPhonetic": "up-BHOK-taa" },
  "distributor": { "hi": "वितरक", "hiPhonetic": "vi-TA-rak" },
  "monopoly": { "hi": "एकाधिकार", "hiPhonetic": "e-kaa-DHI-kaar" },
  "demand (economic)": { "hi": "माँग", "hiPhonetic": "MAANG" },
  "supply (economic)": { "hi": "आपूर्ति", "hiPhonetic": "aa-POOR-ti" },
  "pricing": { "hi": "मूल्य निर्धारण", "hiPhonetic": "MOOL-ya nir-DHAA-ran" },
  "trunk (tree)": { "hi": "तना", "hiPhonetic": "TA-naa" },
  "branch (tree)": { "hi": "शाखा", "hiPhonetic": "SHAA-khaa" },
  "buds": { "hi": "कलियाँ", "hiPhonetic": "ka-LI-yaan" },
  "bark (tree)": { "hi": "छाल", "hiPhonetic": "CHHAAL" }
}
