{
  "they will see": { "hi": "वे देखेंगे", "hiPhonetic": "ve DE-khen-ge" },
  "received": { "hi": "प्राप्त किया", "hiPhonetic": "PRAAP-ta ki-yaa" },
  "thanked": { "hi": "धन्यवाद दिया", "hiPhonetic": "DHAN-ya-vaad DI-yaa" },
  "greeted": { "hi": "अभिवादन किया", "hiPhonetic": "a-bhi-VAA-dan ki-yaa" },
  "she explained": { "hi": "उसने समझाया", "hiPhonetic": "US-ne sam-JHAA-yaa" },
  "was looking for": { "hi": "ढूँढ रहा था", "hiPhonetic": "DHOONDH ra-HAA thaa" },
  "entered": { "hi": "अंदर आया/आई", "hiPhonetic": "AN-dar AA-yaa/AA-ee" },
  "sat for a while": { "hi": "थोड़ी देर बैठा/बैठी", "hiPhonetic": "THO-ree der BAITH-aa/BAITH-ee" },
  "are located": { "hi": "स्थित हैं", "hiPhonetic": "STHI-ta hain" },
  "meets": { "hi": "मिलता है", "hiPhonetic": "MIL-taa hai" },
  "I will join": { "hi": "मैं शामिल होऊँगा", "hiPhonetic": "main SHAA-mil ho-OON-gaa" },
  "worries": { "hi": "चिंता करता है", "hiPhonetic": "CHIN-taa kar-taa hai" },
  "sleeps": { "hi": "सोता है", "hiPhonetic": "SO-taa hai" },
  "I study": { "hi": "मैं पढ़ता हूँ", "hiPhonetic": "main PARH-taa hoon" },
  "to spend (time)": { "hi": "बिताना", "hiPhonetic": "bi-TAA-naa" },
  "knows": { "hi": "जानता है", "hiPhonetic": "JAAN-taa hai" },
  "to call/is named": { "hi": "बुलाना/नाम है", "hiPhonetic": "bu-LAA-naa/NAAM hai" },
  "to keep/to hold": { "hi": "रखना", "hiPhonetic": "RAKH-naa" },
  "shines": { "hi": "चमकता है", "hiPhonetic": "CHAM-ak-taa hai" },
  "I read": { "hi": "मैं पढ़ता हूँ", "hiPhonetic": "main PARH-taa hoon" },
  "was reading": { "hi": "पढ़ रहा था", "hiPhonetic": "PARH ra-HAA thaa" },
  "is/are (there is)": { "hi": "है/हैं", "hiPhonetic": "HAI/HAIN" },
  "was (masculine)": { "hi": "था", "hiPhonetic": "THAA" },
  "was (feminine)": { "hi": "थी", "hiPhonetic": "THEE" },
  "was (neuter)": { "hi": "था", "hiPhonetic": "THAA" }
}
