{
  "outsourcing": {"fr": "externalisation", "frPhonetic": "eks-tair-nah-lee-zah-SYOH"},
  "salamander": {"fr": "salamandre", "frPhonetic": "sah-lah-MAHN-druh"},
  "newt": {"fr": "triton", "frPhonetic": "tree-TOH"},
  "bat (animal)": {"fr": "chauve-souris", "frPhonetic": "SHOHV-soo-REE"},
  "weasel": {"fr": "belette", "frPhonetic": "buh-LET"},
  "otter": {"fr": "loutre", "frPhonetic": "LOO-truh"},
  "polecat/ferret": {"fr": "putois", "frPhonetic": "pew-TWA"},
  "panda": {"fr": "panda", "frPhonetic": "pahn-DAH"},
  "leopard": {"fr": "léopard", "frPhonetic": "lay-oh-PAR"},
  "cheetah": {"fr": "guépard", "frPhonetic": "gay-PAR"},
  "buffalo": {"fr": "buffle", "frPhonetic": "BEW-fluh"},
  "antelope": {"fr": "antilope", "frPhonetic": "ahn-tee-LOP"},
  "gazelle": {"fr": "gazelle", "frPhonetic": "gah-ZEL"},
  "llama": {"fr": "lama", "frPhonetic": "lah-MAH"},
  "alpaca": {"fr": "alpaga", "frPhonetic": "al-pah-GAH"},
  "ferret": {"fr": "furet", "frPhonetic": "few-RAY"},
  "chinchilla": {"fr": "chinchilla", "frPhonetic": "sheh-shee-YAH"},
  "raccoon": {"fr": "raton laveur", "frPhonetic": "rah-TOH lah-VUR"},
  "skunk": {"fr": "mouffette", "frPhonetic": "moo-FET"},
  "opossum": {"fr": "opossum", "frPhonetic": "oh-poh-SOM"},
  "tent": {"fr": "tente", "frPhonetic": "TAHNT"},
  "sleeping bag": {"fr": "sac de couchage", "frPhonetic": "SAK duh koo-SHAZH"},
  "campfire/bonfire": {"fr": "feu de camp", "frPhonetic": "FUH duh KAH"},
  "torch": {"fr": "torche", "frPhonetic": "TORSH"},
  "map": {"fr": "carte", "frPhonetic": "KART"}
}
