{
  "Halloween": {"fr": "Halloween", "frPhonetic": "a-lo-WEEN"},
  "Shrovetide/Maslenitsa": {"fr": "Mardi Gras/Maslenitsa", "frPhonetic": "mar-dee-GRA/mas-leh-NEE-tsa"},
  "Kupala Night": {"fr": "Nuit de Kupala", "frPhonetic": "nwee-duh-koo-PA-la"},
  "geography (subject)": {"fr": "géographie", "frPhonetic": "zhay-oh-gra-FEE"},
  "sociology": {"fr": "sociologie", "frPhonetic": "so-syo-lo-ZHEE"},
  "psychology (subject)": {"fr": "psychologie", "frPhonetic": "psy-ko-lo-ZHEE"},
  "scholarship": {"fr": "bourse", "frPhonetic": "BOORS"},
  "rainy": {"fr": "pluvieux", "frPhonetic": "plu-VYUH"},
  "snowy": {"fr": "neigeux", "frPhonetic": "neh-ZHUH"},
  "hot (weather)": {"fr": "chaud", "frPhonetic": "SHO"},
  "cool (weather)": {"fr": "frais", "frPhonetic": "FREH"},
  "humid/damp": {"fr": "humide", "frPhonetic": "u-MEED"},
  "dry/arid": {"fr": "sec/aride", "frPhonetic": "SEK/a-REED"},
  "stormy": {"fr": "orageux", "frPhonetic": "o-ra-ZHUH"},
  "icicle": {"fr": "stalactite de glace", "frPhonetic": "sta-lak-TEET-duh-GLAS"},
  "to allow/permit": {"fr": "permettre", "frPhonetic": "pehr-METR"},
  "to forbid/prohibit": {"fr": "interdire", "frPhonetic": "an-tehr-DEER"},
  "to order/command": {"fr": "ordonner", "frPhonetic": "or-do-NAY"},
  "to ask/request": {"fr": "demander", "frPhonetic": "duh-man-DAY"},
  "to beg/plead": {"fr": "supplier", "frPhonetic": "su-plye-AY"},
  "to teach/instruct": {"fr": "enseigner", "frPhonetic": "an-seh-NYAY"},
  "to study/learn": {"fr": "étudier", "frPhonetic": "ay-tu-DYAY"},
  "to memorize/remember": {"fr": "mémoriser", "frPhonetic": "may-mo-ree-ZAY"},
  "to commit/obligate": {"fr": "s'engager", "frPhonetic": "san-ga-ZHAY"},
  "to fire/dismiss": {"fr": "licencier", "frPhonetic": "lee-san-SYAY"}
}
