{
  "sticky": {"el": "κολλώδης", "elPhonetic": "ko-LO-dhis"},
  "fragile/brittle": {"el": "εύθραυστος", "elPhonetic": "EF-thraf-stos"},
  "sturdy/strong": {"el": "γερός", "elPhonetic": "yhe-ROS"},
  "elastic/springy": {"el": "ελαστικός", "elPhonetic": "e-las-ti-KOS"},
  "rectangular": {"el": "ορθογώνιος", "elPhonetic": "or-tho-GO-ni-os"},
  "square (shape)": {"el": "τετράγωνος", "elPhonetic": "te-TRA-gho-nos"},
  "triangular": {"el": "τριγωνικός", "elPhonetic": "tri-gho-ni-KOS"},
  "acidic/sour": {"el": "ξινός", "elPhonetic": "ksi-NOS"},
  "bland/unsalted": {"el": "άνοστος", "elPhonetic": "A-nos-tos"},
  "spicy/aromatic": {"el": "μυρωδάτος", "elPhonetic": "mi-ro-DA-tos"},
  "fresh": {"el": "φρέσκος", "elPhonetic": "FRES-kos"},
  "stale": {"el": "μπαγιάτικος", "elPhonetic": "ba-YA-ti-kos"},
  "spoiled/rotten": {"el": "χαλασμένος", "elPhonetic": "ha-laz-ME-nos"},
  "raw/damp": {"el": "ωμός", "elPhonetic": "o-MOS"},
  "fried": {"el": "τηγανητός", "elPhonetic": "ti-gha-ni-TOS"},
  "boiled": {"el": "βραστός", "elPhonetic": "vras-TOS"},
  "baked": {"el": "ψητός", "elPhonetic": "psi-TOS"},
  "frozen": {"el": "κατεψυγμένος", "elPhonetic": "ka-te-psigh-ME-nos"},
  "married": {"el": "παντρεμένος", "elPhonetic": "pan-dre-ME-nos"},
  "unmarried/single": {"el": "ανύπαντρος", "elPhonetic": "a-NI-pan-dros"},
  "pregnant": {"el": "έγκυος", "elPhonetic": "EN-gi-os"},
  "drunk": {"el": "μεθυσμένος", "elPhonetic": "me-this-ME-nos"},
  "sober": {"el": "νηφάλιος", "elPhonetic": "ni-FA-li-os"},
  "open": {"el": "ανοιχτός", "elPhonetic": "a-nih-TOS"},
  "closed": {"el": "κλειστός", "elPhonetic": "klis-TOS"}
}
