{
  "rolling pin": {"el": "πλάστης", "elPhonetic": "PLAS-tis"},
  "bowl": {"el": "μπολ", "elPhonetic": "bol"},
  "tray/platter": {"el": "δίσκος", "elPhonetic": "DHIS-kos"},
  "napkin holder": {"el": "θήκη χαρτοπετσέτας", "elPhonetic": "THI-ki har-to-pet-SE-tas"},
  "salt shaker": {"el": "αλατιέρα", "elPhonetic": "a-la-tYE-ra"},
  "pepper shaker": {"el": "πιπεριέρα", "elPhonetic": "pi-pe-rYE-ra"},
  "sugar bowl": {"el": "ζαχαριέρα", "elPhonetic": "za-ha-rYE-ra"},
  "milk jug/creamer": {"el": "γαλατιέρα", "elPhonetic": "ga-la-tYE-ra"},
  "teapot": {"el": "τσαγιέρα", "elPhonetic": "tsa-YE-ra"},
  "porcelain dishes": {"el": "πορσελάνινα πιάτα", "elPhonetic": "por-se-LA-ni-na PYA-ta"},
  "cutlery": {"el": "μαχαιροπίρουνα", "elPhonetic": "ma-he-ro-PI-ru-na"},
  "tablecloth": {"el": "τραπεζομάντηλο", "elPhonetic": "tra-pe-zo-MAN-di-lo"},
  "candleholder": {"el": "κηροπήγιο", "elPhonetic": "ki-ro-PI-yo"},
  "lampshade": {"el": "καπέλο λάμπας", "elPhonetic": "ka-PE-lo LAM-bas"},
  "chandelier": {"el": "πολυέλαιος", "elPhonetic": "po-li-E-le-os"},
  "floor lamp": {"el": "φωτιστικό δαπέδου", "elPhonetic": "fo-tis-ti-KO dha-PE-dhu"},
  "nightlight": {"el": "νυχτερινό φωτάκι", "elPhonetic": "nih-te-ri-NO fo-TA-ki"},
  "alarm clock": {"el": "ξυπνητήρι", "elPhonetic": "ksip-ni-TI-ri"},
  "thermos": {"el": "θερμός", "elPhonetic": "ther-MOS"},
  "pot (plant)": {"el": "γλάστρα", "elPhonetic": "GLAS-tra"},
  "flowerpot": {"el": "γλάστρα λουλουδιών", "elPhonetic": "GLAS-tra lu-lu-DHYON"},
  "remote control": {"el": "τηλεχειριστήριο", "elPhonetic": "ti-le-hi-ris-TI-ri-o"},
  "antenna": {"el": "κεραία", "elPhonetic": "ke-RE-a"},
  "electrical outlet": {"el": "πρίζα", "elPhonetic": "PRI-za"},
  "extension cord": {"el": "προέκταση", "elPhonetic": "pro-EK-ta-si"}
}
